MANIFEST.in
README.md
setup.py
django_shop_richcatalog.egg-info/PKG-INFO
django_shop_richcatalog.egg-info/SOURCES.txt
django_shop_richcatalog.egg-info/dependency_links.txt
django_shop_richcatalog.egg-info/not-zip-safe
django_shop_richcatalog.egg-info/requires.txt
django_shop_richcatalog.egg-info/top_level.txt
requirements/common.txt
requirements/testing.txt
shop_richcatalog/__init__.py
shop_richcatalog/admin.py
shop_richcatalog/cms_app.py
shop_richcatalog/cms_plugins.py
shop_richcatalog/models.py
shop_richcatalog/tests.py
shop_richcatalog/urls.py
shop_richcatalog/views.py
shop_richcatalog/migrations/0001_initial.py
shop_richcatalog/migrations/0002_catalogplugin.py
shop_richcatalog/migrations/0003_auto_20160316_0846.py
shop_richcatalog/migrations/0004_catalogplugin_root_catalog.py
shop_richcatalog/migrations/0005_update_related_name.py
shop_richcatalog/migrations/__init__.py
shop_richcatalog/south_migrations/0001_initial.py
shop_richcatalog/south_migrations/0002_auto__chg_field_catalog_image.py
shop_richcatalog/south_migrations/__init__.py
shop_richcatalog/templates/catalog/catalog_detail.html
shop_richcatalog/templates/catalog/catalog_grid_plugin.html
shop_richcatalog/templates/catalog/catalog_list.html