Metadata-Version: 1.0
Name: django-shop-richcatalog
Version: 3.1.0
Summary: Rich catalog functionality for django shop.
Home-page: UNKNOWN
Author: Nimbis Services, Inc.
Author-email: devops@nimbisservices.com
License: BSD
Platform: UNKNOWN
